multi_level_maze/__init__.py
multi_level_maze/registration.py
multi_level_maze/envs/__init__.py
multi_level_maze/envs/multi_level_maze_env.py
multi_level_maze-1.0.0.dist-info/licenses/COPYING
multi_level_maze-1.0.0.dist-info/METADATA
multi_level_maze-1.0.0.dist-info/WHEEL
multi_level_maze-1.0.0.dist-info/top_level.txt
multi_level_maze-1.0.0.dist-info/RECORD
