Metadata-Version: 2.4
Name: multi-level-maze
Version: 1.0.0
Summary: A hierarchical multi-level maze environment for Gymnasium
Author-email: Ali Jahani <alijahani@gmx.com>
License: GPL-3.0-or-later
Keywords: reinforcement-learning,gymnasium,maze,environment,hierarchical,nested,multi-level
Classifier: Programming Language :: Python :: 3
Classifier: License :: OSI Approved :: GNU General Public License v3 or later (GPLv3+)
Classifier: Operating System :: OS Independent
Classifier: Topic :: Scientific/Engineering :: Artificial Intelligence
Requires-Python: >=3.9
License-File: COPYING
Requires-Dist: gymnasium>=1.2.1
Requires-Dist: numpy>=1.22
Requires-Dist: pygame>=2.5
Dynamic: license-file
